acad/__init__.py
acad/anomaly_detection.py
acad/isolation_forest.py
acad/kmeans.py
acad/pca.py
acad/streaming_anomaly_detection.py
tests/__init__.py
tests/est_anomaly_detection.py
tests/test-kmeans.py
tests/test_isolation_forest.py
tests/test_pca.py
tests/test_streaming_anomaly_detection.py
acad-0.1.0.dist-info/LICENSE.txt
acad-0.1.0.dist-info/METADATA
acad-0.1.0.dist-info/WHEEL
acad-0.1.0.dist-info/top_level.txt
acad-0.1.0.dist-info/RECORD
