Metadata-Version: 2.1
Name: acad
Version: 0.1.0
Summary: Adaptive Clustering and Anomaly Detection
Author: Your Name
Author-email: quadxome@gmail.com
Classifier: Programming Language :: Python :: 3
Classifier: License :: OSI Approved :: MIT License
Classifier: Operating System :: OS Independent
Requires-Python: >=3.6
License-File: LICENSE.txt
Requires-Dist: numpy
Requires-Dist: scikit-learn
